odoo/addons/project_timesheet_holidays_integrity/README.rst
odoo/addons/project_timesheet_holidays_integrity/__init__.py
odoo/addons/project_timesheet_holidays_integrity/__manifest__.py
odoo/addons/project_timesheet_holidays_integrity/i18n/project_timesheet_holidays_integrity.pot
odoo/addons/project_timesheet_holidays_integrity/models/__init__.py
odoo/addons/project_timesheet_holidays_integrity/models/account_analytic_line.py
odoo/addons/project_timesheet_holidays_integrity/models/hr_leave.py
odoo/addons/project_timesheet_holidays_integrity/readme/CONTRIBUTORS.rst
odoo/addons/project_timesheet_holidays_integrity/readme/DESCRIPTION.rst
odoo/addons/project_timesheet_holidays_integrity/readme/USAGE.rst
odoo/addons/project_timesheet_holidays_integrity/static/description/icon.png
odoo/addons/project_timesheet_holidays_integrity/static/description/index.html
odoo/addons/project_timesheet_holidays_integrity/tests/__init__.py
odoo/addons/project_timesheet_holidays_integrity/tests/test_project_timesheet_holidays_integrity.py
odoo/addons/project_timesheet_holidays_integrity/views/account_analytic_line.xml
odoo/addons/project_timesheet_holidays_integrity/views/hr_leave.xml
odoo12_addon_project_timesheet_holidays_integrity-12.0.1.0.1.dist-info/METADATA
odoo12_addon_project_timesheet_holidays_integrity-12.0.1.0.1.dist-info/WHEEL
odoo12_addon_project_timesheet_holidays_integrity-12.0.1.0.1.dist-info/top_level.txt
odoo12_addon_project_timesheet_holidays_integrity-12.0.1.0.1.dist-info/RECORD
